vulqano/__init__.py
vulqano/compiler.py
vulqano/markoviandynamics.py
vulqano/mcmc.py
vulqano/quantumdynamics.py
vulqano/utils.py
vulqano/version.py
vulqano/circuit_tester/__init__.py
vulqano/circuit_tester/matchatea_interface.py
vulqano/circuit_tester/operations.py
vulqano/circuit_tester/read_qasm.py
vulqano/gates/__init__.py
vulqano/gates/continuousgates.py
vulqano/gates/discretegates.py
vulqano/hamiltonians/__init__.py
vulqano/hamiltonians/mchamiltonians.py
vulqano/quantummodels/__init__.py
vulqano/quantummodels/collapsedquantummodel.py
vulqano/quantummodels/localquantumops.py
vulqano/quantummodels/quantummodel.py
vulqano/rules/__init__.py
vulqano/rules/abstractcontinuousrules.py
vulqano/rules/abstractdiscreterules.py
vulqano/rules/mcrules.py
vulqano/rules/standardcontinuousrules.py
vulqano/rules/standarddiscreterules.py
vulqano/rules/sym4rules.py
vulqano/states/__init__.py
vulqano/states/abstractcircuitstate.py
vulqano/states/mcstates.py
vulqano-0.1.2.dist-info/LICENSE
vulqano-0.1.2.dist-info/METADATA
vulqano-0.1.2.dist-info/WHEEL
vulqano-0.1.2.dist-info/top_level.txt
vulqano-0.1.2.dist-info/RECORD
