Metadata-Version: 2.1
Name: vulqano
Version: 0.1.2
Summary: Compiler for quantum algorithms
Home-page: https://baltig.infn.it/qpd/vulqano.git
Author: Davide Rattacaso, Daniel Jaschke, Marco Ballarin
Author-email: 
Classifier: Programming Language :: Python :: 3
Classifier: Operating System :: OS Independent
Requires-Python: >=3.8
License-File: LICENSE
Requires-Dist: qiskit ==0.38.0
Requires-Dist: qtealeaves >=1.1.10
Requires-Dist: numpy
Requires-Dist: matplotlib
Requires-Dist: tqdm
Requires-Dist: multiprocess
